LICENSE.txt
README.md
setup.cfg
setup.py
topsis_rahul_101903508/topsis_rahul_101903508.py
topsis_rahul_101903508.egg-info/PKG-INFO
topsis_rahul_101903508.egg-info/SOURCES.txt
topsis_rahul_101903508.egg-info/dependency_links.txt
topsis_rahul_101903508.egg-info/requires.txt
topsis_rahul_101903508.egg-info/top_level.txt