Metadata-Version: 2.1
Name: topsis-rahul-101903508
Version: 0.1
Summary: Topsis
Home-page: https://github.com/rahul21200/topsis_rahul_101903508
Author: Rahul Kapoor
Author-email: rahulkapoor902@gmail.com
License: MIT
Download-URL: https://github.com/rahul21200/topsis_rahul_101903508/archive/refs/tags/v_01.tar.gz
Keywords: SOME,MEANINGFULL,KEYWORDS
Platform: UNKNOWN
Classifier: Development Status :: 3 - Alpha
Classifier: Intended Audience :: Developers
Classifier: Topic :: Software Development :: Build Tools
Classifier: License :: OSI Approved :: MIT License
Classifier: Programming Language :: Python :: 3
Classifier: Programming Language :: Python :: 3.4
Classifier: Programming Language :: Python :: 3.5
Classifier: Programming Language :: Python :: 3.6
License-File: LICENSE.txt
